podcasts/__init__.py
podcasts-0.0.1.dist-info/LICENSE
podcasts-0.0.1.dist-info/METADATA
podcasts-0.0.1.dist-info/WHEEL
podcasts-0.0.1.dist-info/top_level.txt
podcasts-0.0.1.dist-info/RECORD
