Metadata-Version: 2.1
Name: podcasts
Version: 0.0.1
Summary: Parse podcasts with Python
Home-page: https://github.com/pypodcasts/podcasts
Author: Jorrin Pollard
Author-email: hi@jorr.in
License: MIT
Keywords: podcasts
Platform: UNKNOWN
Classifier: Development Status :: 3 - Alpha
Classifier: Environment :: Console
Classifier: Intended Audience :: End Users/Desktop
Classifier: License :: OSI Approved :: MIT License
Classifier: Natural Language :: English
Classifier: Operating System :: OS Independent
Classifier: Programming Language :: Python :: 3
Classifier: Topic :: Multimedia :: Sound/Audio
